mypy_xml_score/__init__.py
mypy_xml_score/__main__.py
mypy_xml_score/mypy_xml_score.xslt
mypy_xml_score/py.typed
mypy_xml_score-0.5.dist-info/LICENCE.txt
mypy_xml_score-0.5.dist-info/METADATA
mypy_xml_score-0.5.dist-info/WHEEL
mypy_xml_score-0.5.dist-info/entry_points.txt
mypy_xml_score-0.5.dist-info/top_level.txt
mypy_xml_score-0.5.dist-info/RECORD
